se_best_practices_ml_perspective/__init__.py
se_best_practices_ml_perspective/main.py
se_best_practices_ml_perspective/main_with_stylistic_errors.py
se_best_practices_ml_perspective-0.1.1.dist-info/LICENSE
se_best_practices_ml_perspective-0.1.1.dist-info/WHEEL
se_best_practices_ml_perspective-0.1.1.dist-info/METADATA
se_best_practices_ml_perspective-0.1.1.dist-info/RECORD
